opensafely/VERSION
opensafely/__init__.py
opensafely/clean.py
opensafely/codelists.py
opensafely/execute.py
opensafely/extract_stats.py
opensafely/info.py
opensafely/jupyter.py
opensafely/launch.py
opensafely/pull.py
opensafely/rstudio.py
opensafely/unzip.py
opensafely/upgrade.py
opensafely/utils.py
opensafely/_vendor/deprecated.pyi
opensafely/_vendor/pipeline.pyi
opensafely/_vendor/requests.pyi
opensafely/_vendor/wrapt.pyi
opensafely/_vendor/zipp.pyi
opensafely/_vendor/certifi/__init__.py
opensafely/_vendor/certifi/__main__.py
opensafely/_vendor/certifi/cacert.pem
opensafely/_vendor/certifi/core.py
opensafely/_vendor/certifi/py.typed
opensafely/_vendor/charset_normalizer/__init__.py
opensafely/_vendor/charset_normalizer/__main__.py
opensafely/_vendor/charset_normalizer/api.py
opensafely/_vendor/charset_normalizer/cd.py
opensafely/_vendor/charset_normalizer/constant.py
opensafely/_vendor/charset_normalizer/legacy.py
opensafely/_vendor/charset_normalizer/md.py
opensafely/_vendor/charset_normalizer/models.py
opensafely/_vendor/charset_normalizer/py.typed
opensafely/_vendor/charset_normalizer/utils.py
opensafely/_vendor/charset_normalizer/version.py
opensafely/_vendor/charset_normalizer/cli/__init__.py
opensafely/_vendor/charset_normalizer/cli/__main__.py
opensafely/_vendor/deprecated/__init__.py
opensafely/_vendor/deprecated/classic.py
opensafely/_vendor/deprecated/sphinx.py
opensafely/_vendor/distro/__init__.py
opensafely/_vendor/distro/__main__.py
opensafely/_vendor/distro/distro.py
opensafely/_vendor/distro/py.typed
opensafely/_vendor/idna/__init__.py
opensafely/_vendor/idna/codec.py
opensafely/_vendor/idna/compat.py
opensafely/_vendor/idna/core.py
opensafely/_vendor/idna/idnadata.py
opensafely/_vendor/idna/intranges.py
opensafely/_vendor/idna/package_data.py
opensafely/_vendor/idna/py.typed
opensafely/_vendor/idna/uts46data.py
opensafely/_vendor/importlib_metadata/__init__.py
opensafely/_vendor/importlib_metadata/_adapters.py
opensafely-1.56.2.dist-info/LICENSE
opensafely-1.56.2.dist-info/METADATA
opensafely-1.56.2.dist-info/WHEEL
opensafely-1.56.2.dist-info/entry_points.txt
opensafely-1.56.2.dist-info/top_level.txt
opensafely-1.56.2.dist-info/RECORD
