Metadata-Version: 2.1
Name: opensafely
Version: 1.56.2
Summary: Command line tool for running OpenSAFELY studies locally.
Author-email: OpenSAFELY <tech@opensafely.org>
License: GPL-3.0
Project-URL: Homepage, https://opensafely.org
Project-URL: Documentation, https://docs.opensafely.org
Project-URL: Repository, https://github.com/opensafely-core/opensafely-cli
Project-URL: Bug Reports, https://github.com/opensafely-core/opensafely-cli/issues
Project-URL: Source, https://github.com/opensafely-core/opensafely-cli
Keywords: opensafely,epidemiology,research
Classifier: Development Status :: 4 - Beta
Classifier: Environment :: Console
Classifier: Intended Audience :: Science/Research
Classifier: Programming Language :: Python :: 3
Classifier: Programming Language :: Python :: 3.8
Classifier: Programming Language :: Python :: 3.9
Classifier: Programming Language :: Python :: 3.10
Classifier: Programming Language :: Python :: 3.11
Classifier: Programming Language :: Python :: 3.12
Classifier: Programming Language :: Python :: 3.13
Classifier: Topic :: Scientific/Engineering
Requires-Python: >=3.8
License-File: LICENSE
Provides-Extra: tracing
Requires-Dist: opentelemetry-api==1.33.1; extra == "tracing"
Requires-Dist: opentelemetry-sdk==1.33.1; extra == "tracing"
Requires-Dist: opentelemetry-exporter-otlp-proto-http==1.15.0; extra == "tracing"
